Flask_WeChat-0.1.0.dist-info/DESCRIPTION.rst
Flask_WeChat-0.1.0.dist-info/METADATA
Flask_WeChat-0.1.0.dist-info/RECORD
Flask_WeChat-0.1.0.dist-info/WHEEL
Flask_WeChat-0.1.0.dist-info/metadata.json
Flask_WeChat-0.1.0.dist-info/top_level.txt
flask_wechat/__init__.py
flask_wechat/apiclient.py
flask_wechat/callback.py
flask_wechat/filters.py
flask_wechat/signals.py
