Metadata-Version: 2.0
Name: Flask-WeChat
Version: 0.1.0
Summary: a simple flask extension for setup wechat service.
Home-page: https://github.com/Xavier-Lam/flask-wechat
Author: Xavier-Lam
Author-email: lam.xavier@hotmail.com
License: UNKNOWN
Keywords: flask,wechat,weixin,micromessage
Platform: UNKNOWN
Classifier: Programming Language :: Python
Classifier: Programming Language :: Python :: 2
Classifier: Programming Language :: Python :: 2.7
Classifier: Programming Language :: Python :: 3
Classifier: Programming Language :: Python :: Implementation
Classifier: Development Status :: 3 - Alpha
Classifier: Environment :: Web Environment
Classifier: Framework :: Flask
Classifier: Intended Audience :: Developers
Classifier: Operating System :: OS Independent
Classifier: Natural Language :: Chinese (Simplified)
Classifier: Natural Language :: English
Classifier: Topic :: Internet :: WWW/HTTP :: Dynamic Content
Classifier: Topic :: Software Development :: Libraries :: Python Modules
Requires-Dist: Flask (==0.10.1)
Requires-Dist: requests (==2.9.1)
